LICENSE
MANIFEST.in
NEWS.md
README.md
setup.py
scorecardpy/__init__.py
scorecardpy/condition_fun.py
scorecardpy/germancredit.py
scorecardpy/info_ent_indx_gini.py
scorecardpy/info_value.py
scorecardpy/one_hot.py
scorecardpy/perf.py
scorecardpy/scorecard.py
scorecardpy/split_df.py
scorecardpy/var_filter.py
scorecardpy/vif.py
scorecardpy/woebin.py
scorecardpy.egg-info/PKG-INFO
scorecardpy.egg-info/SOURCES.txt
scorecardpy.egg-info/dependency_links.txt
scorecardpy.egg-info/requires.txt
scorecardpy.egg-info/top_level.txt
scorecardpy/data/germancredit.csv