Metadata-Version: 2.1
Name: scorecardpy
Version: 0.1.9.6
Summary: Credit Risk Scorecard
Home-page: http://github.com/shichenxie/scorecardpy
Author: Shichen Xie
Author-email: xie@shichen.name
Project-URL: Bug Reports, https://github.com/shichenxie/scorecardpy/issues
Project-URL: Source, https://github.com/shichenxie/scorecardpy/
Keywords: credit scorecard,woe binning,performace evaluation
Classifier: Development Status :: 4 - Beta
Classifier: Intended Audience :: Developers
Classifier: License :: OSI Approved :: MIT License
Classifier: Programming Language :: Python :: 3
Classifier: Programming Language :: Python :: 3.4
Classifier: Programming Language :: Python :: 3.5
Classifier: Programming Language :: Python :: 3.6
Classifier: Programming Language :: Python :: 3.7
Classifier: Programming Language :: Python :: 3.8
Classifier: Programming Language :: Python :: 3.9
Classifier: Programming Language :: Python :: 3.10
License-File: LICENSE
